FF23004UNO/__init__.py
FF23004UNO/metodos.py
ff23004uno-0.1.dist-info/METADATA
ff23004uno-0.1.dist-info/WHEEL
ff23004uno-0.1.dist-info/top_level.txt
ff23004uno-0.1.dist-info/RECORD
