Metadata-Version: 2.4
Name: FF23004UNO
Version: 0.1
Summary: Librería para resolver sistemas de ecuaciones lineales y no lineales
Author: Jonathan Fuentes
Keywords: gauss,jacobi,Descomposición LU,Crammer,Gauss-Jordan,Eliminación de Gauss,bisección,sistemas de ecuaciones,CARNETFF23004
Classifier: Programming Language :: Python :: 3
Classifier: Operating System :: OS Independent
Requires-Dist: numpy
Requires-Dist: scipy
Dynamic: author
Dynamic: classifier
Dynamic: keywords
Dynamic: requires-dist
Dynamic: summary
